dagster_ssh/__init__.py
dagster_ssh/resources.py
dagster_ssh/version.py
dagster_ssh-1.0.5.dist-info/LICENSE
dagster_ssh-1.0.5.dist-info/METADATA
dagster_ssh-1.0.5.dist-info/WHEEL
dagster_ssh-1.0.5.dist-info/top_level.txt
dagster_ssh-1.0.5.dist-info/RECORD
